auxeticmop/AbaqusScripts.py
auxeticmop/FileIO.py
auxeticmop/GeneticAlgorithm.py
auxeticmop/GraphicUserInterface.py
auxeticmop/MutateAndValidate.py
auxeticmop/Network.py
auxeticmop/ParameterDefinitions.py
auxeticmop/PostProcessing.py
auxeticmop/__init__.py
auxeticmop/sample_scripts/Step1_Randomly_generates_parent_topologies.py
auxeticmop/sample_scripts/Step2_Generate_offspring_topologies.py
auxeticmop/sample_scripts/Step3_Evaluate_fitness_values_and_select.py
auxeticmop/sample_scripts/__init__.py
auxeticmop/sample_scripts/full_steps.py
auxeticmop/sample_scripts/sample_data/FieldOutput_1
auxeticmop/sample_scripts/sample_data/FieldOutput_offspring_1
auxeticmop/sample_scripts/sample_data/Topologies_1
auxeticmop-1.0.2.dist-info/LICENSE
auxeticmop-1.0.2.dist-info/METADATA
auxeticmop-1.0.2.dist-info/WHEEL
auxeticmop-1.0.2.dist-info/top_level.txt
auxeticmop-1.0.2.dist-info/RECORD
