Metadata-Version: 2.1
Name: auxeticmop
Version: 1.0.2
Summary: A package for finding meta-material structure using ABAQUS and MOP evolutionary algorithm approaches.
Home-page: https://github.com/c0sogi/AuxeticMOP-with-ABAQUS
Author: Seongbin Choi
Author-email: dcas@naver.com
License: MIT
Classifier: Programming Language :: Python :: 3
Classifier: License :: OSI Approved :: MIT License
Classifier: Operating System :: Microsoft :: Windows
Requires-Python: >=3.6,<3.11
License-File: LICENSE
Requires-Dist: numpy
Requires-Dist: numba
Requires-Dist: aiofiles
Requires-Dist: matplotlib
Requires-Dist: scipy
Requires-Dist: dataclasses
